_polyclipNP.cpython-311-darwin.so
polyclipNP.py
polyclipNP-0.4.dist-info/METADATA
polyclipNP-0.4.dist-info/WHEEL
polyclipNP-0.4.dist-info/top_level.txt
polyclipNP-0.4.dist-info/RECORD
