Metadata-Version: 2.1
Name: polyclipNP
Version: 0.4
Summary: Swig wrapper of polyclip.c from J.D. Smith
Author: N. Pirzkal
